{"Document Title": [], "Document Number": [{"text": "20Document", "x1": 1056, "y1": 106, "x2": 1463, "y2": 164}, {"text": "1600", "x1": 168, "y1": 226, "x2": 222, "y2": 246}, {"text": "200", "x1": 508, "y1": 226, "x2": 549, "y2": 246}, {"text": "85282", "x1": 299, "y1": 264, "x2": 368, "y2": 283}, {"text": "33-1256", "x1": 816, "y1": 532, "x2": 924, "y2": 556}, {"text": "33-1807", "x1": 1013, "y1": 531, "x2": 1123, "y2": 555}, {"text": "33-1256", "x1": 565, "y1": 619, "x2": 661, "y2": 639}, {"text": "2002-0987138", "x1": 626, "y1": 677, "x2": 795, "y2": 698}, {"text": "2002", "x1": 1036, "y1": 677, "x2": 1093, "y2": 698}, {"text": "629", "x1": 344, "y1": 821, "x2": 387, "y2": 842}, {"text": "2003-589722", "x1": 1323, "y1": 821, "x2": 1478, "y2": 842}, {"text": "2004-652468", "x1": 428, "y1": 852, "x2": 583, "y2": 873}, {"text": "23200", "x1": 546, "y1": 929, "x2": 616, "y2": 949}, {"text": "85326-6186", "x1": 713, "y1": 965, "x2": 847, "y2": 985}, {"text": "33-1256", "x1": 1093, "y1": 1182, "x2": 1186, "y2": 1201}, {"text": "33-1807", "x1": 1245, "y1": 1181, "x2": 1336, "y2": 1202}, {"text": "2021", "x1": 1305, "y1": 1550, "x2": 1356, "y2": 1570}], "Return to Address": [{"text": "33-1256", "x1": 816, "y1": 532, "x2": 924, "y2": 556}], "Dated Date": [], "Recording Date": [], "Recording Fee": [{"text": "1600", "x1": 168, "y1": 226, "x2": 222, "y2": 246}, {"text": "200", "x1": 508, "y1": 226, "x2": 549, "y2": 246}, {"text": "85282", "x1": 299, "y1": 264, "x2": 368, "y2": 283}, {"text": "2002", "x1": 1036, "y1": 677, "x2": 1093, "y2": 698}, {"text": "224,", "x1": 1161, "y1": 760, "x2": 1211, "y2": 784}, {"text": "629", "x1": 344, "y1": 821, "x2": 387, "y2": 842}, {"text": "23200", "x1": 546, "y1": 929, "x2": 616, "y2": 949}, {"text": "2021,", "x1": 687, "y1": 1129, "x2": 751, "y2": 1153}, {"text": "2021.", "x1": 1304, "y1": 1264, "x2": 1365, "y2": 1284}, {"text": "2021", "x1": 1305, "y1": 1550, "x2": 1356, "y2": 1570}], "Debtors Name": [], "Debtors Address": [{"text": "33-1256", "x1": 816, "y1": 532, "x2": 924, "y2": 556}], "Notary Name": [], "Lien Amount": [{"text": "1600", "x1": 168, "y1": 226, "x2": 222, "y2": 246}, {"text": "200", "x1": 508, "y1": 226, "x2": 549, "y2": 246}, {"text": "85282", "x1": 299, "y1": 264, "x2": 368, "y2": 283}, {"text": "2002", "x1": 1036, "y1": 677, "x2": 1093, "y2": 698}, {"text": "224,", "x1": 1161, "y1": 760, "x2": 1211, "y2": 784}, {"text": "629", "x1": 344, "y1": 821, "x2": 387, "y2": 842}, {"text": "23200", "x1": 546, "y1": 929, "x2": 616, "y2": 949}, {"text": "2021,", "x1": 687, "y1": 1129, "x2": 751, "y2": 1153}, {"text": "2021.", "x1": 1304, "y1": 1264, "x2": 1365, "y2": 1284}, {"text": "2021", "x1": 1305, "y1": 1550, "x2": 1356, "y2": 1570}], "Recording Book": [{"text": "20Document", "x1": 1056, "y1": 106, "x2": 1463, "y2": 164}, {"text": "1600", "x1": 168, "y1": 226, "x2": 222, "y2": 246}, {"text": "200", "x1": 508, "y1": 226, "x2": 549, "y2": 246}, {"text": "85282", "x1": 299, "y1": 264, "x2": 368, "y2": 283}, {"text": "33-1256", "x1": 816, "y1": 532, "x2": 924, "y2": 556}, {"text": "33-1807", "x1": 1013, "y1": 531, "x2": 1123, "y2": 555}, {"text": "33-1256", "x1": 565, "y1": 619, "x2": 661, "y2": 639}, {"text": "2002-0987138", "x1": 626, "y1": 677, "x2": 795, "y2": 698}, {"text": "2002", "x1": 1036, "y1": 677, "x2": 1093, "y2": 698}, {"text": "629", "x1": 344, "y1": 821, "x2": 387, "y2": 842}, {"text": "2003-589722", "x1": 1323, "y1": 821, "x2": 1478, "y2": 842}, {"text": "2004-652468", "x1": 428, "y1": 852, "x2": 583, "y2": 873}, {"text": "23200", "x1": 546, "y1": 929, "x2": 616, "y2": 949}, {"text": "85326-6186", "x1": 713, "y1": 965, "x2": 847, "y2": 985}, {"text": "33-1256", "x1": 1093, "y1": 1182, "x2": 1186, "y2": 1201}, {"text": "33-1807", "x1": 1245, "y1": 1181, "x2": 1336, "y2": 1202}, {"text": "2021", "x1": 1305, "y1": 1550, "x2": 1356, "y2": 1570}], "Recording Page": [{"text": "20Document", "x1": 1056, "y1": 106, "x2": 1463, "y2": 164}, {"text": "1600", "x1": 168, "y1": 226, "x2": 222, "y2": 246}, {"text": "200", "x1": 508, "y1": 226, "x2": 549, "y2": 246}, {"text": "85282", "x1": 299, "y1": 264, "x2": 368, "y2": 283}, {"text": "33-1256", "x1": 816, "y1": 532, "x2": 924, "y2": 556}, {"text": "33-1807", "x1": 1013, "y1": 531, "x2": 1123, "y2": 555}, {"text": "33-1256", "x1": 565, "y1": 619, "x2": 661, "y2": 639}, {"text": "2002-0987138", "x1": 626, "y1": 677, "x2": 795, "y2": 698}, {"text": "2002", "x1": 1036, "y1": 677, "x2": 1093, "y2": 698}, {"text": "629", "x1": 344, "y1": 821, "x2": 387, "y2": 842}, {"text": "2003-589722", "x1": 1323, "y1": 821, "x2": 1478, "y2": 842}, {"text": "2004-652468", "x1": 428, "y1": 852, "x2": 583, "y2": 873}, {"text": "23200", "x1": 546, "y1": 929, "x2": 616, "y2": 949}, {"text": "85326-6186", "x1": 713, "y1": 965, "x2": 847, "y2": 985}, {"text": "33-1256", "x1": 1093, "y1": 1182, "x2": 1186, "y2": 1201}, {"text": "33-1807", "x1": 1245, "y1": 1181, "x2": 1336, "y2": 1202}, {"text": "2021", "x1": 1305, "y1": 1550, "x2": 1356, "y2": 1570}], "Claimant Name": [], "Claimant Address": [{"text": "33-1256", "x1": 816, "y1": 532, "x2": 924, "y2": 556}], "Legal Description": []}