{"Document Title": [], "Document Number": [{"text": "2021-0052304", "x1": 885, "y1": 76, "x2": 1035, "y2": 93}, {"text": "85385", "x1": 979, "y1": 485, "x2": 1046, "y2": 505}, {"text": "B86", "x1": 322, "y1": 846, "x2": 382, "y2": 941}, {"text": "2021", "x1": 1413, "y1": 1481, "x2": 1469, "y2": 1502}, {"text": "e388", "x1": 85, "y1": 1619, "x2": 157, "y2": 1655}, {"text": "2021-0045816", "x1": 410, "y1": 1942, "x2": 573, "y2": 1963}], "Return to Address": [], "Dated Date": [], "Recording Date": [], "Recording Fee": [{"text": "85385", "x1": 979, "y1": 485, "x2": 1046, "y2": 505}, {"text": "2021", "x1": 1413, "y1": 1481, "x2": 1469, "y2": 1502}], "Debtors Name": [], "Debtors Address": [], "Notary Name": [], "Lien Amount": [{"text": "85385", "x1": 979, "y1": 485, "x2": 1046, "y2": 505}, {"text": "2021", "x1": 1413, "y1": 1481, "x2": 1469, "y2": 1502}], "Recording Book": [{"text": "2021-0052304", "x1": 885, "y1": 76, "x2": 1035, "y2": 93}, {"text": "85385", "x1": 979, "y1": 485, "x2": 1046, "y2": 505}, {"text": "B86", "x1": 322, "y1": 846, "x2": 382, "y2": 941}, {"text": "2021", "x1": 1413, "y1": 1481, "x2": 1469, "y2": 1502}, {"text": "e388", "x1": 85, "y1": 1619, "x2": 157, "y2": 1655}, {"text": "2021-0045816", "x1": 410, "y1": 1942, "x2": 573, "y2": 1963}], "Recording Page": [{"text": "2021-0052304", "x1": 885, "y1": 76, "x2": 1035, "y2": 93}, {"text": "85385", "x1": 979, "y1": 485, "x2": 1046, "y2": 505}, {"text": "B86", "x1": 322, "y1": 846, "x2": 382, "y2": 941}, {"text": "2021", "x1": 1413, "y1": 1481, "x2": 1469, "y2": 1502}, {"text": "e388", "x1": 85, "y1": 1619, "x2": 157, "y2": 1655}, {"text": "2021-0045816", "x1": 410, "y1": 1942, "x2": 573, "y2": 1963}], "Claimant Name": [], "Claimant Address": [], "Legal Description": []}