{"Document Title": [], "Document Number": [{"text": "982-302-1604", "x1": 334, "y1": 308, "x2": 559, "y2": 375}, {"text": "18294", "x1": 481, "y1": 353, "x2": 560, "y2": 377}, {"text": "1971", "x1": 759, "y1": 822, "x2": 807, "y2": 842}, {"text": "23255", "x1": 649, "y1": 855, "x2": 737, "y2": 879}, {"text": "NV-89048", "x1": 867, "y1": 923, "x2": 981, "y2": 945}, {"text": "882749", "x1": 1037, "y1": 957, "x2": 1089, "y2": 978}, {"text": "212-5000", "x1": 353, "y1": 1882, "x2": 485, "y2": 1907}], "Return to Address": [], "Dated Date": [], "Recording Date": [], "Recording Fee": [{"text": "18294", "x1": 481, "y1": 353, "x2": 560, "y2": 377}, {"text": "1971", "x1": 759, "y1": 822, "x2": 807, "y2": 842}, {"text": "23255", "x1": 649, "y1": 855, "x2": 737, "y2": 879}, {"text": "25,2017", "x1": 574, "y1": 955, "x2": 668, "y2": 976}, {"text": "882749", "x1": 1037, "y1": 957, "x2": 1089, "y2": 978}], "Debtors Name": [], "Debtors Address": [], "Notary Name": [], "Lien Amount": [{"text": "18294", "x1": 481, "y1": 353, "x2": 560, "y2": 377}, {"text": "1971", "x1": 759, "y1": 822, "x2": 807, "y2": 842}, {"text": "23255", "x1": 649, "y1": 855, "x2": 737, "y2": 879}, {"text": "25,2017", "x1": 574, "y1": 955, "x2": 668, "y2": 976}, {"text": "882749", "x1": 1037, "y1": 957, "x2": 1089, "y2": 978}], "Recording Book": [{"text": "982-302-1604", "x1": 334, "y1": 308, "x2": 559, "y2": 375}, {"text": "18294", "x1": 481, "y1": 353, "x2": 560, "y2": 377}, {"text": "1971", "x1": 759, "y1": 822, "x2": 807, "y2": 842}, {"text": "23255", "x1": 649, "y1": 855, "x2": 737, "y2": 879}, {"text": "NV-89048", "x1": 867, "y1": 923, "x2": 981, "y2": 945}, {"text": "882749", "x1": 1037, "y1": 957, "x2": 1089, "y2": 978}, {"text": "212-5000", "x1": 353, "y1": 1882, "x2": 485, "y2": 1907}], "Recording Page": [{"text": "982-302-1604", "x1": 334, "y1": 308, "x2": 559, "y2": 375}, {"text": "18294", "x1": 481, "y1": 353, "x2": 560, "y2": 377}, {"text": "1971", "x1": 759, "y1": 822, "x2": 807, "y2": 842}, {"text": "23255", "x1": 649, "y1": 855, "x2": 737, "y2": 879}, {"text": "NV-89048", "x1": 867, "y1": 923, "x2": 981, "y2": 945}, {"text": "882749", "x1": 1037, "y1": 957, "x2": 1089, "y2": 978}, {"text": "212-5000", "x1": 353, "y1": 1882, "x2": 485, "y2": 1907}], "Claimant Name": [], "Claimant Address": [], "Legal Description": []}